{"se3_1_01179_gen":{"prefix":["Se3_1_01179_gene"],"exact":[]},"se3_1_00721_":{"prefix":["Se3_1_00721_gene"],"exact":[]},"se3_1_00974":{"prefix":["Se3_1_00974_gene"],"exact":[]},"se3_1_01192_g":{"exact":[],"prefix":["Se3_1_01192_gene"]},"se3_1_01062_gen":{"prefix":["Se3_1_01062_gene"],"exact":[]},"se3_1_01591":{"exact":[],"prefix":["Se3_1_01591_gene"]},"se3_1_02037_gene":{"prefix":[],"exact":[["Se3_1_02037_gene",0,"yfcE","gnl__MG__Se3_1_1",2048985,2049504]]},"se3_1_01930_gen":{"exact":[],"prefix":["Se3_1_01930_gene"]},"se3_1_01680_gene":{"prefix":[],"exact":[["Se3_1_01680_gene",0,"araQ_2","gnl__MG__Se3_1_1",1676870,1677719]]},"se3_1_00333_gen":{"exact":[],"prefix":["Se3_1_00333_gene"]},"se3_1_0147":{"prefix":["Se3_1_01470_gene","Se3_1_01471_gene","Se3_1_01472_gene","Se3_1_01473_gene","Se3_1_01474_gene","Se3_1_01475_gene","Se3_1_01476_gene","Se3_1_01477_gene","Se3_1_01478_gene","Se3_1_01479_gene"],"exact":[]},"se3_1_00380":{"exact":[],"prefix":["Se3_1_00380_gene"]},"se3_1_01312":{"exact":[],"prefix":["Se3_1_01312_gene"]},"se3_1_00286_ge":{"prefix":["Se3_1_00286_gene"],"exact":[]},"se3_1_00503":{"exact":[],"prefix":["Se3_1_00503_gene"]},"se3_1_01839_gene":{"prefix":[],"exact":[["Se3_1_01839_gene",0,"malX","gnl__MG__Se3_1_1",1826847,1828071]]},"se3_1_00071":{"prefix":["Se3_1_00071_gene"],"exact":[]},"se3_1_02038_ge":{"exact":[],"prefix":["Se3_1_02038_gene"]},"se3_1_00956_g":{"prefix":["Se3_1_00956_gene"],"exact":[]},"se3_1_01148_gene":{"prefix":[],"exact":[["Se3_1_01148_gene",0,"galE_1","gnl__MG__Se3_1_1",1147258,1148251]]},"se3_1_01277_ge":{"exact":[],"prefix":["Se3_1_01277_gene"]},"se3_1_00400_ge":{"exact":[],"prefix":["Se3_1_00400_gene"]},"se3_1_01223_":{"prefix":["Se3_1_01223_gene"],"exact":[]},"se3_1_01463_":{"exact":[],"prefix":["Se3_1_01463_gene"]},"se3_1_01434_gen":{"exact":[],"prefix":["Se3_1_01434_gene"]},"se3_1_00756_gene":{"exact":[["Se3_1_00756_gene",0,"nadE","gnl__MG__Se3_1_1",781043,781871]],"prefix":[]},"se3_1_01336_ge":{"prefix":["Se3_1_01336_gene"],"exact":[]},"se3_1_00175_gene":{"prefix":[],"exact":[["Se3_1_00175_gene",0,"Se3_1_00175_gene","gnl__MG__Se3_1_1",181306,182107]]},"se3_1_00780_gen":{"prefix":["Se3_1_00780_gene"],"exact":[]},"yh":{"prefix":["yheI","yhhX","yhaO","yhaM","yhjX"],"exact":[]},"se3_1_00804_gene":{"exact":[["Se3_1_00804_gene",0,"Se3_1_00804_gene","gnl__MG__Se3_1_1",827051,827642]],"prefix":[]},"se3_1_02199":{"exact":[],"prefix":["Se3_1_02199_gene"]},"se3_1_00228_gen":{"exact":[],"prefix":["Se3_1_00228_gene"]},"se3_1_02034":{"exact":[],"prefix":["Se3_1_02034_gene"]},"se3_1_01660":{"exact":[],"prefix":["Se3_1_01660_gene"]},"se3_1_01413_gene":{"prefix":[],"exact":[["Se3_1_01413_gene",0,"Se3_1_01413_gene","gnl__MG__Se3_1_1",1407321,1407684]]},"ni":{"prefix":["niaX"],"exact":[]},"yjjg":{"exact":[["yjjG",0,"yjjG","gnl__MG__Se3_1_1",242136,242934]],"prefix":[]},"se3_1_02179_ge":{"prefix":["Se3_1_02179_gene"],"exact":[]},"se3_1_00582_g":{"prefix":["Se3_1_00582_gene"],"exact":[]},"se3_1_00161_":{"prefix":["Se3_1_00161_gene"],"exact":[]},"cits":{"prefix":[],"exact":[["citS",0,"citS","gnl__MG__Se3_1_1",293197,294478]]},"se3_1_01087_gen":{"prefix":["Se3_1_01087_gene"],"exact":[]},"se3_1_00932_g":{"prefix":["Se3_1_00932_gene"],"exact":[]},"se3_1_00541_ge":{"prefix":["Se3_1_00541_gene"],"exact":[]},"se3_1_01230_gene":{"exact":[["Se3_1_01230_gene",0,"Se3_1_01230_gene","gnl__MG__Se3_1_1",1217328,1218579]],"prefix":[]},"se3_1_00765_gen":{"exact":[],"prefix":["Se3_1_00765_gene"]},"csb":{"prefix":["csbB_1","csbB_2"],"exact":[]},"se3_1_00935_":{"prefix":["Se3_1_00935_gene"],"exact":[]}}