{"se3_1_00352":{"exact":[],"prefix":["Se3_1_00352_gene"]},"se3_1_00212_gene":{"exact":[["Se3_1_00212_gene",0,"gltB_1","gnl__MG__Se3_1_1",212573,214013]],"prefix":[]},"se3_1_02013_ge":{"exact":[],"prefix":["Se3_1_02013_gene"]},"se3_1_00732_g":{"exact":[],"prefix":["Se3_1_00732_gene"]},"se3_1_00670_gen":{"prefix":["Se3_1_00670_gene"],"exact":[]},"se3_1_00756_g":{"prefix":["Se3_1_00756_gene"],"exact":[]},"se3_1_01089_gen":{"prefix":["Se3_1_01089_gene"],"exact":[]},"rpst":{"prefix":[],"exact":[["rpsT",0,"rpsT","gnl__MG__Se3_1_1",1998336,1998591]]},"se3_1_01411_ge":{"prefix":["Se3_1_01411_gene"],"exact":[]},"murj":{"prefix":["murJ_1","murJ_2"],"exact":[]},"se3_1_01163_g":{"prefix":["Se3_1_01163_gene"],"exact":[]},"coad":{"exact":[["coaD",0,"coaD","gnl__MG__Se3_1_1",1192962,1193445]],"prefix":[]},"se3_1_00431_gene":{"exact":[["Se3_1_00431_gene",0,"acr3","gnl__MG__Se3_1_1",438248,439310]],"prefix":[]},"se3_1_01327_":{"exact":[],"prefix":["Se3_1_01327_gene"]},"se3_1_01825_gen":{"prefix":["Se3_1_01825_gene"],"exact":[]},"se3_1_01297_ge":{"exact":[],"prefix":["Se3_1_01297_gene"]},"se3_1_00226_gen":{"prefix":["Se3_1_00226_gene"],"exact":[]},"se3_1_00065_":{"exact":[],"prefix":["Se3_1_00065_gene"]},"ndk":{"prefix":[],"exact":[["ndk",0,"ndk","gnl__MG__Se3_1_1",26454,26868]]},"se3_1_01346_g":{"prefix":["Se3_1_01346_gene"],"exact":[]},"se3_1_01107_g":{"exact":[],"prefix":["Se3_1_01107_gene"]},"se3_1_01550_ge":{"prefix":["Se3_1_01550_gene"],"exact":[]},"se3_1_01899":{"prefix":["Se3_1_01899_gene"],"exact":[]},"se3_1_00620":{"exact":[],"prefix":["Se3_1_00620_gene"]},"se3_1_02028_gene":{"prefix":[],"exact":[["Se3_1_02028_gene",0,"yxdM","gnl__MG__Se3_1_1",2030101,2032078]]},"se3_1_01279_":{"prefix":["Se3_1_01279_gene"],"exact":[]},"se3_1_00573_g":{"prefix":["Se3_1_00573_gene"],"exact":[]},"cyse_2":{"prefix":[],"exact":[["cysE_2",0,"cysE_2","gnl__MG__Se3_1_1",1623213,1623807]]},"se3_1_01322_g":{"prefix":["Se3_1_01322_gene"],"exact":[]},"se3_1_01192_gen":{"prefix":["Se3_1_01192_gene"],"exact":[]},"se3_1_01157_gene":{"prefix":[],"exact":[["Se3_1_01157_gene",0,"rppH_2","gnl__MG__Se3_1_1",1155421,1155922]]},"se3_1_01031":{"prefix":["Se3_1_01031_gene"],"exact":[]},"cdr_1":{"prefix":[],"exact":[["cdr_1",0,"cdr_1","gnl__MG__Se3_1_1",436572,438234]]},"se3_1_01774_gene":{"exact":[["Se3_1_01774_gene",0,"Se3_1_01774_gene","gnl__MG__Se3_1_1",1767943,1769053]],"prefix":[]},"se3_1_01567_":{"exact":[],"prefix":["Se3_1_01567_gene"]},"se3_1_02152_ge":{"exact":[],"prefix":["Se3_1_02152_gene"]},"psp":{"prefix":["pspB"],"exact":[]},"se3_1_0195":{"prefix":["Se3_1_01950_gene","Se3_1_01951_gene","Se3_1_01952_gene","Se3_1_01953_gene","Se3_1_01954_gene","Se3_1_01955_gene","Se3_1_01956_gene","Se3_1_01957_gene","Se3_1_01958_gene","Se3_1_01959_gene"],"exact":[]},"se3_1_01934":{"exact":[],"prefix":["Se3_1_01934_gene"]},"se3_1_00625_":{"prefix":["Se3_1_00625_gene"],"exact":[]},"se3_1_01521_gen":{"exact":[],"prefix":["Se3_1_01521_gene"]},"se3_1_02199_ge":{"prefix":["Se3_1_02199_gene"],"exact":[]},"se3_1_01177_gen":{"exact":[],"prefix":["Se3_1_01177_gene"]},"lag":{"exact":[],"prefix":["lagD"]},"se3_1_00081_gene":{"exact":[["Se3_1_00081_gene",0,"Se3_1_00081_gene","gnl__MG__Se3_1_1",85495,86314]],"prefix":[]},"se3_1_00695_gen":{"exact":[],"prefix":["Se3_1_00695_gene"]},"se3_1_00749_gene":{"prefix":[],"exact":[["Se3_1_00749_gene",0,"rpmB","gnl__MG__Se3_1_1",774111,774300]]},"ltas":{"exact":[],"prefix":["ltaS1"]},"se3_1_0038":{"exact":[],"prefix":["Se3_1_00380_gene","Se3_1_00381_gene","Se3_1_00382_gene","Se3_1_00383_gene","Se3_1_00384_gene","Se3_1_00385_gene","Se3_1_00386_gene","Se3_1_00387_gene","Se3_1_00388_gene","Se3_1_00389_gene"]},"se3_1_00327_ge":{"prefix":["Se3_1_00327_gene"],"exact":[]},"se3_1_01826_gene":{"exact":[["Se3_1_01826_gene",0,"sorC_3","gnl__MG__Se3_1_1",1815877,1816687]],"prefix":[]},"se3_1_01543":{"prefix":["Se3_1_01543_gene"],"exact":[]},"se3_1_00831_":{"exact":[],"prefix":["Se3_1_00831_gene"]},"azor1":{"exact":[["azoR1",0,"azoR1","gnl__MG__Se3_1_1",703289,703538]],"prefix":[]},"se3_1_01439_":{"exact":[],"prefix":["Se3_1_01439_gene"]},"iscu":{"prefix":[],"exact":[["iscU",0,"iscU","gnl__MG__Se3_1_1",488971,489445]]},"inlj_2":{"exact":[["inlJ_2",0,"inlJ_2","gnl__MG__Se3_1_1",1180228,1180840]],"prefix":[]},"se3_1_00266_ge":{"prefix":["Se3_1_00266_gene"],"exact":[]},"se3_1_00517_g":{"exact":[],"prefix":["Se3_1_00517_gene"]}}