{"se3_1_02067_g":{"exact":[],"prefix":["Se3_1_02067_gene"]},"se3_1_01899_gen":{"prefix":["Se3_1_01899_gene"],"exact":[]},"nn":{"prefix":["nnrD"],"exact":[]},"se3_1_01630_":{"exact":[],"prefix":["Se3_1_01630_gene"]},"se3_1_00973":{"exact":[],"prefix":["Se3_1_00973_gene"]},"se3_1_00031_ge":{"exact":[],"prefix":["Se3_1_00031_gene"]},"se3_1_00971_gene":{"exact":[["Se3_1_00971_gene",0,"dtd","gnl__MG__Se3_1_1",976693,977197]],"prefix":[]},"se3_1_00298_g":{"exact":[],"prefix":["Se3_1_00298_gene"]},"se3_1_02033":{"prefix":["Se3_1_02033_gene"],"exact":[]},"se3_1_01646_ge":{"exact":[],"prefix":["Se3_1_01646_gene"]},"se3_1_01035_gen":{"exact":[],"prefix":["Se3_1_01035_gene"]},"se3_1_00076":{"exact":[],"prefix":["Se3_1_00076_gene"]},"se3_1_00364_gen":{"prefix":["Se3_1_00364_gene"],"exact":[]},"yo":{"prefix":["yodC","yofA","yocH","yohK"],"exact":[]},"se3_1_01315":{"exact":[],"prefix":["Se3_1_01315_gene"]},"se3_1_00075_g":{"exact":[],"prefix":["Se3_1_00075_gene"]},"se3_1_01149":{"prefix":["Se3_1_01149_gene"],"exact":[]},"se3_1_01982_gen":{"prefix":["Se3_1_01982_gene"],"exact":[]},"se3_1_02162_":{"prefix":["Se3_1_02162_gene"],"exact":[]},"se3_1_00234_g":{"prefix":["Se3_1_00234_gene"],"exact":[]},"se3_1_02003_g":{"exact":[],"prefix":["Se3_1_02003_gene"]},"se3_1_01688_g":{"prefix":["Se3_1_01688_gene"],"exact":[]},"se3_1_01465_g":{"prefix":["Se3_1_01465_gene"],"exact":[]},"se3_1_01345_gene":{"prefix":[],"exact":[["Se3_1_01345_gene",0,"codY","gnl__MG__Se3_1_1",1332283,1333072]]},"fcf":{"exact":[],"prefix":["fcf1"]},"se3_1_00011_g":{"exact":[],"prefix":["Se3_1_00011_gene"]},"se3_1_01640_g":{"exact":[],"prefix":["Se3_1_01640_gene"]},"se3_1_00758":{"prefix":["Se3_1_00758_gene"],"exact":[]},"se3_1_00572_":{"exact":[],"prefix":["Se3_1_00572_gene"]},"se3_1_00629_gen":{"exact":[],"prefix":["Se3_1_00629_gene"]},"se3_1_02142_gene":{"prefix":[],"exact":[["Se3_1_02142_gene",0,"araC","gnl__MG__Se3_1_1",2147531,2148401]]},"se3_1_01824_":{"prefix":["Se3_1_01824_gene"],"exact":[]},"se3_1_00250_g":{"exact":[],"prefix":["Se3_1_00250_gene"]},"se3_1_00293_gene":{"exact":[["Se3_1_00293_gene",0,"tetD","gnl__MG__Se3_1_1",300480,301344]],"prefix":[]},"se3_1_00623_gene":{"exact":[["Se3_1_00623_gene",0,"Se3_1_00623_gene","gnl__MG__Se3_1_1",637184,637508]],"prefix":[]},"se3_1_01463_gen":{"exact":[],"prefix":["Se3_1_01463_gene"]},"se3_1_01070_":{"prefix":["Se3_1_01070_gene"],"exact":[]},"se3_1_01566_gene":{"prefix":[],"exact":[["Se3_1_01566_gene",0,"Se3_1_01566_gene","gnl__MG__Se3_1_1",1556006,1558271]]},"se3_1_00387":{"prefix":["Se3_1_00387_gene"],"exact":[]},"pnc":{"prefix":["pncB2"],"exact":[]},"se3_1_01624_g":{"exact":[],"prefix":["Se3_1_01624_gene"]},"se3_1_01707_ge":{"prefix":["Se3_1_01707_gene"],"exact":[]},"se3_1_01667":{"exact":[],"prefix":["Se3_1_01667_gene"]},"se3_1_01957_ge":{"prefix":["Se3_1_01957_gene"],"exact":[]},"se3_1_01967_gen":{"exact":[],"prefix":["Se3_1_01967_gene"]},"se3_1_00170_ge":{"exact":[],"prefix":["Se3_1_00170_gene"]},"se3_1_01578_gen":{"prefix":["Se3_1_01578_gene"],"exact":[]},"se3_1_01181_ge":{"prefix":["Se3_1_01181_gene"],"exact":[]},"se3_1_00504":{"prefix":["Se3_1_00504_gene"],"exact":[]},"se3_1_01879_g":{"exact":[],"prefix":["Se3_1_01879_gene"]},"se3_1_00378_gene":{"exact":[["Se3_1_00378_gene",0,"Se3_1_00378_gene","gnl__MG__Se3_1_1",384809,385322]],"prefix":[]},"se3_1_01816_ge":{"prefix":["Se3_1_01816_gene"],"exact":[]},"se3_1_0140":{"prefix":["Se3_1_01400_gene","Se3_1_01401_gene","Se3_1_01402_gene","Se3_1_01403_gene","Se3_1_01404_gene","Se3_1_01405_gene","Se3_1_01406_gene","Se3_1_01407_gene","Se3_1_01408_gene","Se3_1_01409_gene"],"exact":[]},"se3_1_00332_":{"prefix":["Se3_1_00332_gene"],"exact":[]},"se3_1_01401_g":{"prefix":["Se3_1_01401_gene"],"exact":[]},"se3_1_00381_gen":{"prefix":["Se3_1_00381_gene"],"exact":[]},"se3_1_01596":{"prefix":["Se3_1_01596_gene"],"exact":[]},"se3_1_00732_gen":{"prefix":["Se3_1_00732_gene"],"exact":[]},"cdd":{"exact":[["cdd",0,"cdd","gnl__MG__Se3_1_1",103313,103706]],"prefix":[]},"se3_1_01486_gen":{"prefix":["Se3_1_01486_gene"],"exact":[]}}