{"se3_1_01227_":{"exact":[],"prefix":["Se3_1_01227_gene"]},"se3_1_00746_g":{"prefix":["Se3_1_00746_gene"],"exact":[]},"se3_1_00543":{"exact":[],"prefix":["Se3_1_00543_gene"]},"se3_1_01186_gene":{"prefix":[],"exact":[["Se3_1_01186_gene",0,"fus","gnl__MG__Se3_1_1",1182466,1184542]]},"se3_1_02012_ge":{"prefix":["Se3_1_02012_gene"],"exact":[]},"se3_1_02112_gene":{"prefix":[],"exact":[["Se3_1_02112_gene",0,"Se3_1_02112_gene","gnl__MG__Se3_1_1",2118208,2119129]]},"glnm":{"exact":[],"prefix":["glnM_1","glnM_2"]},"mngr_1":{"prefix":[],"exact":[["mngR_1",0,"mngR_1","gnl__MG__Se3_1_1",1478457,1479183]]},"se3_1_01831_gen":{"prefix":["Se3_1_01831_gene"],"exact":[]},"se3_1_01535_gen":{"prefix":["Se3_1_01535_gene"],"exact":[]},"se3_1_01410_ge":{"exact":[],"prefix":["Se3_1_01410_gene"]},"se3_1_01551_ge":{"prefix":["Se3_1_01551_gene"],"exact":[]},"se3_1_01352":{"exact":[],"prefix":["Se3_1_01352_gene"]},"se3_1_01186_gen":{"exact":[],"prefix":["Se3_1_01186_gene"]},"se3_1_02153_ge":{"exact":[],"prefix":["Se3_1_02153_gene"]},"se3_1_01536_gene":{"prefix":[],"exact":[["Se3_1_01536_gene",0,"Se3_1_01536_gene","gnl__MG__Se3_1_1",1533931,1534204]]},"se3_1_01356_g":{"exact":[],"prefix":["Se3_1_01356_gene"]},"se3_1_00563_g":{"prefix":["Se3_1_00563_gene"],"exact":[]},"se3_1_00934":{"prefix":["Se3_1_00934_gene"],"exact":[]},"se3_1_01539_":{"prefix":["Se3_1_01539_gene"],"exact":[]},"ktra_2":{"prefix":[],"exact":[["ktrA_2",0,"ktrA_2","gnl__MG__Se3_1_1",2181868,2182522]]},"se3_1_01379_":{"exact":[],"prefix":["Se3_1_01379_gene"]},"se3_1_01163_gen":{"exact":[],"prefix":["Se3_1_01163_gene"]},"se3_1_00673_gene":{"prefix":[],"exact":[["Se3_1_00673_gene",0,"yacL","gnl__MG__Se3_1_1",689370,690444]]},"se3_1_02074":{"prefix":["Se3_1_02074_gene"],"exact":[]},"se3_1_01296_ge":{"exact":[],"prefix":["Se3_1_01296_gene"]},"kbay":{"exact":[["kbaY",0,"kbaY","gnl__MG__Se3_1_1",358024,358870]],"prefix":[]},"se3_1_00725_":{"exact":[],"prefix":["Se3_1_00725_gene"]},"se3_1_00681_gen":{"prefix":["Se3_1_00681_gene"],"exact":[]},"se3_1_01332_g":{"exact":[],"prefix":["Se3_1_01332_gene"]},"se3_1_00899":{"prefix":["Se3_1_00899_gene"],"exact":[]},"se3_1_00722_g":{"exact":[],"prefix":["Se3_1_00722_gene"]},"se3_1_00931_":{"exact":[],"prefix":["Se3_1_00931_gene"]},"se3_1_01117_g":{"prefix":["Se3_1_01117_gene"],"exact":[]},"se3_1_02198_ge":{"exact":[],"prefix":["Se3_1_02198_gene"]},"se3_1_01467_":{"exact":[],"prefix":["Se3_1_01467_gene"]},"se3_1_00326_ge":{"exact":[],"prefix":["Se3_1_00326_gene"]},"se3_1_0107":{"exact":[],"prefix":["Se3_1_01070_gene","Se3_1_01071_gene","Se3_1_01072_gene","Se3_1_01073_gene","Se3_1_01074_gene","Se3_1_01075_gene","Se3_1_01076_gene","Se3_1_01077_gene","Se3_1_01078_gene","Se3_1_01079_gene"]},"se3_1_01315_gene":{"prefix":[],"exact":[["Se3_1_01315_gene",0,"rnmV","gnl__MG__Se3_1_1",1302373,1302946]]},"se3_1_00507_g":{"prefix":["Se3_1_00507_gene"],"exact":[]},"yutf":{"exact":[["yutF",0,"yutF","gnl__MG__Se3_1_1",2203049,2203814]],"prefix":[]},"se3_1_00031":{"exact":[],"prefix":["Se3_1_00031_gene"]},"se3_1_00267_ge":{"prefix":["Se3_1_00267_gene"],"exact":[]},"se3_1_00664_gen":{"exact":[],"prefix":["Se3_1_00664_gene"]},"se3_1_00232_gen":{"exact":[],"prefix":["Se3_1_00232_gene"]},"se3_1_00165_":{"exact":[],"prefix":["Se3_1_00165_gene"]},"se3_1_00329_gen":{"prefix":["Se3_1_00329_gene"],"exact":[]},"se3_1_00050_gene":{"exact":[["Se3_1_00050_gene",0,"Se3_1_00050_gene","gnl__MG__Se3_1_1",55577,55772]],"prefix":[]},"se3_1_01078_gen":{"prefix":["Se3_1_01078_gene"],"exact":[]},"se3_1_00328_gene":{"exact":[["Se3_1_00328_gene",0,"accC","gnl__MG__Se3_1_1",336176,337547]],"prefix":[]},"se3_1_01173_g":{"exact":[],"prefix":["Se3_1_01173_gene"]},"yja":{"exact":[],"prefix":["yjaB"]},"se3_1_00798_gene":{"exact":[["Se3_1_00798_gene",0,"Se3_1_00798_gene","gnl__MG__Se3_1_1",820856,821423]],"prefix":[]},"se3_1_00921_gene":{"prefix":[],"exact":[["Se3_1_00921_gene",0,"Se3_1_00921_gene","gnl__MG__Se3_1_1",927786,930456]]},"se3_1_01620":{"prefix":["Se3_1_01620_gene"],"exact":[]},"potd":{"exact":[["potD",0,"potD","gnl__MG__Se3_1_1",2110713,2111787]],"prefix":[]},"trub":{"prefix":[],"exact":[["truB",0,"truB","gnl__MG__Se3_1_1",2207635,2208532]]}}